export_edit_import/__init__.py
export_edit_import/admin.py
export_edit_import/apps.py
export_edit_import/base_choice_mapping.py
export_edit_import/business_validator.py
export_edit_import/create_export_excel_file.py
export_edit_import/database_processor.py
export_edit_import/enums.py
export_edit_import/error_file_generator.py
export_edit_import/formats.py
export_edit_import/import_processors.py
export_edit_import/models.py
export_edit_import/tests.py
export_edit_import/utils.py
export_edit_import/views.py
export_edit_import/migrations/0001_initial.py
export_edit_import/migrations/__init__.py
django_export_edit_import-1.0.2.dist-info/METADATA
django_export_edit_import-1.0.2.dist-info/WHEEL
django_export_edit_import-1.0.2.dist-info/top_level.txt
django_export_edit_import-1.0.2.dist-info/RECORD
