Metadata-Version: 2.4
Name: django-export-edit-import
Version: 1.0.2
Summary: Reusable Django app that enables export, edit and import (Excel) workflow.
Author: Daniil Pevzner
License: MIT
Project-URL: Source, https://github.com/PevznerDanill/django-export-edit-import-package
Classifier: Framework :: Django
Classifier: Framework :: Django :: 4
Classifier: Programming Language :: Python :: 3 :: Only
Classifier: Programming Language :: Python :: 3.9
Classifier: Programming Language :: Python :: 3.10
Classifier: Programming Language :: Python :: 3.11
Classifier: Programming Language :: Python :: 3.12
Classifier: Development Status :: 4 - Beta
Classifier: Intended Audience :: Developers
Classifier: License :: OSI Approved :: MIT License
Classifier: Operating System :: OS Independent
Classifier: Topic :: Software Development :: Libraries :: Python Modules
Requires-Python: >=3.9
Requires-Dist: Django>=4.2
Requires-Dist: pandas>=2.0
Requires-Dist: openpyxl>=3.1
Provides-Extra: dev
Requires-Dist: pytest; extra == "dev"
Requires-Dist: pytest-django; extra == "dev"
Requires-Dist: black; extra == "dev"
Requires-Dist: isort; extra == "dev"
Requires-Dist: flake8; extra == "dev"
